<?xml version="1.0" encoding="UTF-8"?>
<!--
	Copyright (C) 2013-2016 Nanjing StarOS Technology Co., Ltd
	All rights reserved.
	
	@file 		MonitorAPIHandler.xml monitor_
	@brief 		Monitor的增删改查
	@version 	1.1.0
	@auth 		hu peng (hupeng@staros.xyz)
	@date		2017/11/27

	Licensed under the Apache License, Version 2.0 (the "License");
	you may not use this file except in compliance with the License.
	You may obtain a copy of the License at

	http://www.apache.org/licenses/LICENSE-2.0

	Unless required by applicable law or agreed to in writing, software
	distributed under the License is distributed on an "AS IS" BASIS,
	WITHOUT WARRANTIES OR CONDITIONS OF ANY KIND, either express or implied.
	See the License for the specific language governing permissions and
	limitations under the License.
-->
<starlang xmlns="http://www.staros.xyz/starcore/xml" xmlns:xsi="http://www.w3.org/2001/XMLSchema-instance" scope="application">
	<!--
		@brief		注册APP 到RestfulService
		@auth 		qiulei
		@date		20180109
		Input:
			@param filename 	CRestfulService.xml
		  	@param xmldata   	getCurrentBundleId
		Output: 

	-->

	<function name="monitor_RegisterHandler">
		<log>insert tunnelserviceapi RegisterHandler</log>
		
		
		<function name="RegisterAPIHandler" class="RestfulService">
			<parameters>
				<long name="bundleid" in="context.getCurrentBundleId()"/>			
				<string name="handleevent" in="'processmonitorsrequest'"/>
				<string name="requestpathtest" in="'/onos/v1/monitor/monitors'"/>			
			</parameters>
		</function>

		<function name="RegisterAPIHandler" class="RestfulService">
			<parameters>
				<long name="bundleid" in="context.getCurrentBundleId()"/>			
				<string name="handleevent" in="'processcreateonemonitorrequest'"/>
				<string name="requestpathtest" in="'/onos/v1/monitor/monitor'"/>			
			</parameters>
		</function>
		
		<function name="RegisterAPIHandler" class="RestfulService">
			<parameters>
				<long name="bundleid" in="context.getCurrentBundleId()"/>			
				<string name="handleevent" in="'processdeleteormodifyorupdateonemonitorrequest'"/>
				<string name="requestpathtest" in="'/onos/v1/monitor/monitor/{ip}'"/>			
			</parameters>
		</function>

	</function>
	
	<!--
		@brief		注销APP 到RestfulService
		@auth 		qiulei
		@date		20180109
		Input:
			@param filename 	CRestfulService.xml
		  	@param xmldata   	requestpath
		Output: 
		-->

	<function name="monitor_UnRegisterHandler">
		<function name="UnRegisterAPIHandler" class="RestfulService">
			<parameters>
				<string name="requestpath" in="'/onos/v1/monitor/monitors'"/>			
			</parameters>
		</function>

		<function name="UnRegisterAPIHandler" class="RestfulService">
			<parameters>
				<string name="requestpath" in="'/onos/v1/monitor/monitor'"/>			
			</parameters>
		</function>
		
		<function name="UnRegisterAPIHandler" class="RestfulService">
			<parameters>
				<string name="requestpathtest" in="'/onos/v1/monitor/monitor/{ip}'"/>			
			</parameters>
		</function>
	</function>
	
	<events>
		<onevent event="processmonitorsrequest">
			<if cond="event.getParam('method').toString()=='GET'">
				<then>
					<log level="100">得到所有Monitors</log>
					<function name="getAllMonitors"/>
				</then>
				<elseif cond="event.getParam('method').toString()=='POST'">
					<log level="100">创建所有Monitors</log>
					<function name="monitor_successresponse"/>
				</elseif>
			</if>
		</onevent>

		<onevent event="processcreateonemonitorrequest">
			<log level="100">创建一个monitor</log>
			<function name="createOneMonitor"/>
		</onevent>
		
		<onevent event="processdeleteormodifyorupdateonemonitorrequest">
			<if cond="event.getParam('method').toString()=='GET'">
				<then>
					<log level="100">得到一个monitor</log>
					<function name="monitor_successresponse"/>
				</then>
				<elseif cond="event.getParam('method').toString()=='DELETE'">
					<log level="100">删除一个monitor</log>
					<function name="deleOneteMonitorByIp"/>
				</elseif>
				<elseif cond="event.getParam('method').toString()=='PUT'">
					<log level="100">更新一个monitor</log>
					<function name="monitor_successresponse"/>
				</elseif>
			</if>
		</onevent>
	</events>

	

	<function name="getAllMonitors">
		<log level="100">enter getAllMonitors Method  ----MonitorAPIHandler.xml 136</log>
		<string name="allMonitorStr"/>
		<function name="GetALLHostJsonData" class="MonitorManager">
			<parameters>
				<string name="jsonstring" out="context.allMonitorStr"/>
			</parameters>
		</function>
		
		
		<if cond="context.allMonitorStr=='' || context.allMonitorStr==null">
			<then>
				<function name="monitor_ErrorDatasResponse">
					<parameters>
						<string name="monitorip" in="'-1'"/>
						<string name="transportid" in="event.getParam('transportid').toString()"/>
						<string name="description" in="'No monitors found'"/>
					</parameters>
				</function>
				<exit/>
			</then>
		</if>
		
		<function name="SendResponse" class="RestfulService">
			<parameters>
				<string name="transportid" in="event.getParam('transportid').toString()"/>
				<string name="json" in="context.allMonitorStr.toString()"/>
			</parameters>
		</function>
		
		<log level="100"> getAllMonitors over  ----MonitorAPIHandler.xml 165</log>
	</function>
	
	<function name="createOneMonitor">
		<log level="100">enter createOneMonitor Method  ----MonitorAPIHandler.xml 157</log>
		<boolean name="addResult" value="false"/>
		
		<string name="monitorip"/>
		<script><![CDATA[
			context.print("----174 monitor数据="+event.getParam('eventdata').toString());

			var monitorobj = JSON.parse(event.getParam('eventdata').toString());
	
			var monitorip = monitorobj.ip;
			context.print("----177 monitorip="+monitorip);
			context.monitorip.setValue(monitorip);

		]]></script>

		<function name="addMonitor" class="MonitorManager">
			<parameters>
				<string name="ip" in="context.monitorip"/>
				<boolean name="result" out="context.addResult"/>
			</parameters>
		</function>
		<log level="100"><![CDATA[188 addResult=<%=context.addResult.toString()%>  ----MonitorAPIHandler.xml 188]]></log>
		<if cond="context.addResult.toBoolean()==true">
			<then>
				<function name="monitor_successresponse"/>
			</then>
			<else>
				<function name="monitor_ErrorDatasResponse">
					<parameters>
						<string name="monitorip" in="context.monitorip.toString()"/>
						<string name="transportid" in="event.getParam('transportid').toString()"/>
						<string name="description" in="'Create a failure ,because the ip is exixts'"/>
					</parameters>
				</function>
				<exit/>
			</else>
		</if>

		<log level="100">execute createOneMonitor over  ----MonitorAPIHandler.xml 204</log>
	</function>
	
	<function name="deleOneteMonitorByIp">
		<log level="100">enter deleOneteMonitorByIp Method  ----MonitorAPIHandler.xml 260</log>
		<string name="monitorip"/>
		<object name="onemonitor"/>
		<string name="successresponse"/>
		
		<script><![CDATA[
			var str = event.getParam('requestpath').toString();
			
			context.print(" 244 requestpath="+str);
			var arr = str.split("/");
			var monitorip=arr[arr.length-1];
			context.print("----222 monitorip="+monitorip);
			
			context.print('路径id='+monitorip.indexOf("{"));
			
			if(monitorip.indexOf("{")!=-1){
				var thisid=(monitorip.split("{")[1]).split("}")[0];
				context.print("250 thisid="+thisid);
				context.monitorip.setValue(thisid);
			}else{
				context.monitorip.setValue(monitorip);
			}
		]]></script>
		<log level="100"><![CDATA[232 monitorip=<%=context.monitorip.toString()%>  ----MonitorAPIHandler.xml]]></log>
		<boolean name="removeResult" value="false"/>
		
		<function name="RemoveMonitor" class="MonitorManager">
			<parameters>
				<string name="ip" in="context.monitorip.toString()"/>
				<boolean name="result" out="context.removeResult"/>
			</parameters>
		</function>
		<log level="100"><![CDATA[241 removeResult=<%=context.removeResult.toString()%>  ----MonitorAPIHandler.xml]]></log>
		<if cond="context.removeResult.toBoolean()==true">
			<then>
				<function name="monitor_successresponse"/>
				<exit/>
			</then>
			<else>
				<function name="monitor_ErrorDatasResponse">
					<parameters>
						<string name="monitorip" in="context.monitorip"/>
						<string name="transportid" in="event.getParam('transportid').toString()"/>
						<string name="description" in="'This ip is wrong'"/>
					</parameters>
				</function>
				<exit/>
			</else>
		</if>
		<log level="100">execute deleOneteMonitorByIp Method over ----MonitorAPIHandler.xml 260</log>
	</function>

	<function name="monitor_successresponse">
		<string name="response"/>
		<reference variable="response">
			<jsonbody><![CDATA[ 
				{
					"result":{
						"code": "0",
						"description": "ok"
					}
				}
			]]></jsonbody>
		</reference>
		<function name="SendResponse" class="RestfulService">
			<parameters>
				<string name="transportid" in="event.getParam('transportid').toString()"/>
				<string name="json" in="context.response.toString()"/>
			</parameters>
		</function>
	</function>
	
	<function name="monitor_ErrorDatasResponse">
		<parameters>
			<string name="monitorip"/>
			<string name="transportid"/>
			<string name="description"/>
		</parameters>
		<string name="outjson"/>
		<script><![CDATA[
			var json = new Object();
			var one = new Object();
				one.monitorId = context.monitorip.toString();
				one.code = "-1";
				one.description = context.description.toString();						
			json.result = one;
			var strjson=JSON.stringify(json);												
			context.outjson.setValue(strjson);
		]]></script>
		<function name="SendResponse" class="RestfulService">
			<parameters>
				<string name="transportid" in="context.transportid.toString()"/>
				<string name="json" in="context.outjson.toString()"/>
			</parameters>
		</function>
	</function>
</starlang>